.gitignore
README.rst
README.txt
setup.py
pm/__init__.py
pm.recipe.debianize.egg-info/PKG-INFO
pm.recipe.debianize.egg-info/SOURCES.txt
pm.recipe.debianize.egg-info/dependency_links.txt
pm.recipe.debianize.egg-info/entry_points.txt
pm.recipe.debianize.egg-info/namespace_packages.txt
pm.recipe.debianize.egg-info/not-zip-safe
pm.recipe.debianize.egg-info/requires.txt
pm.recipe.debianize.egg-info/top_level.txt
pm/recipe/__init__.py
pm/recipe/debianize/__init__.py
pm/recipe/debianize/core.py
pm/recipe/debianize/script/debianize.sh