Metadata-Version: 1.0
Name: pm.recipe.debianize
Version: 0.8
Summary: A buildout recipe to create debian packages
Home-page: https://github.com/specialunderwear/pm.recipe.debianize
Author: Lars van de Kerkhof
Author-email: lars@permanentmarkers.nl
License: GPL
Keywords: debian buildout
Platform: UNKNOWN
